yctmodel/__init__.py
yctmodel/yctmodel.py
yctmodel-5.4.0.dist-info/LICENSE
yctmodel-5.4.0.dist-info/METADATA
yctmodel-5.4.0.dist-info/WHEEL
yctmodel-5.4.0.dist-info/top_level.txt
yctmodel-5.4.0.dist-info/RECORD
