Metadata-Version: 2.1
Name: yctmodel
Version: 5.4.0
Summary: ModelSelector automates ensemble creation, added AutoTuner.
Home-page: https://github.com/gems-yc4923/thames.git
Author: yc4923
License: MIT
License-File: LICENSE
Requires-Dist: scikit-learn
Requires-Dist: pandas
Requires-Dist: matplotlib
Requires-Dist: numpy
Requires-Dist: scipy
Requires-Dist: seaborn
Requires-Dist: xgboost
